spaik/__init__.py
spaik/example.py
spaik/py.typed
spaik-0.1.0.dist-info/AUTHORS.rst
spaik-0.1.0.dist-info/LICENSE.txt
spaik-0.1.0.dist-info/METADATA
spaik-0.1.0.dist-info/WHEEL
spaik-0.1.0.dist-info/top_level.txt
spaik-0.1.0.dist-info/RECORD
