Metadata-Version: 2.1
Name: spaik
Version: 0.1.0
Summary: Having a conversation in another language.
Home-page: https://github.com/csph/spaik
Author: csph
Author-email: 26927961+csph@users.noreply.github.com
License: commercial
Requires-Python: >=3.9
License-File: LICENSE.txt
License-File: AUTHORS.rst
Requires-Dist: importlib-metadata
Provides-Extra: build
Requires-Dist: build[virtualenv] ==1.0.3 ; extra == 'build'
Provides-Extra: build-template
Requires-Dist: build[virtualenv] ==1.0.3 ; extra == 'build-template'
Provides-Extra: dev
Requires-Dist: tox ==4.11.1 ; extra == 'dev'
Requires-Dist: isort ==5.12.0 ; extra == 'dev'
Requires-Dist: black ==23.7.0 ; extra == 'dev'
Requires-Dist: mypy ==1.5.1 ; extra == 'dev'
Requires-Dist: pylint ==2.17.5 ; extra == 'dev'
Requires-Dist: pydocstyle[toml] ==6.3.0 ; extra == 'dev'
Requires-Dist: pytest ==7.4.1 ; extra == 'dev'
Requires-Dist: types-docutils ; extra == 'dev'
Requires-Dist: types-setuptools ; extra == 'dev'
Requires-Dist: jinja2 ==3.1.2 ; extra == 'dev'
Requires-Dist: pytest-randomly ==3.15.0 ; extra == 'dev'
Requires-Dist: pytest-cov ==4.1.0 ; extra == 'dev'
Requires-Dist: coverage[toml] ==7.3.1 ; extra == 'dev'
Requires-Dist: sphinx ==7.2.6 ; extra == 'dev'
Requires-Dist: sphinx-rtd-theme ==1.3.0 ; extra == 'dev'
Requires-Dist: sphinx-autodoc-typehints ==1.24.0 ; extra == 'dev'
Requires-Dist: pip-licenses ==4.3.2 ; extra == 'dev'
Requires-Dist: build[virtualenv] ==1.0.3 ; extra == 'dev'
Provides-Extra: doc
Requires-Dist: sphinx ==7.2.6 ; extra == 'doc'
Requires-Dist: sphinx-rtd-theme ==1.3.0 ; extra == 'doc'
Requires-Dist: sphinx-autodoc-typehints ==1.24.0 ; extra == 'doc'
Requires-Dist: pip-licenses ==4.3.2 ; extra == 'doc'
Requires-Dist: jinja2 ==3.1.2 ; extra == 'doc'
Provides-Extra: doc-template
Requires-Dist: sphinx ==7.2.6 ; extra == 'doc-template'
Requires-Dist: sphinx-rtd-theme ==1.3.0 ; extra == 'doc-template'
Requires-Dist: sphinx-autodoc-typehints ==1.24.0 ; extra == 'doc-template'
Requires-Dist: pip-licenses ==4.3.2 ; extra == 'doc-template'
Requires-Dist: jinja2 ==3.1.2 ; extra == 'doc-template'
Provides-Extra: lint
Requires-Dist: isort ==5.12.0 ; extra == 'lint'
Requires-Dist: black ==23.7.0 ; extra == 'lint'
Requires-Dist: mypy ==1.5.1 ; extra == 'lint'
Requires-Dist: pylint ==2.17.5 ; extra == 'lint'
Requires-Dist: pydocstyle[toml] ==6.3.0 ; extra == 'lint'
Requires-Dist: pytest ==7.4.1 ; extra == 'lint'
Requires-Dist: types-docutils ; extra == 'lint'
Requires-Dist: types-setuptools ; extra == 'lint'
Requires-Dist: jinja2 ==3.1.2 ; extra == 'lint'
Provides-Extra: lint-template
Requires-Dist: isort ==5.12.0 ; extra == 'lint-template'
Requires-Dist: black ==23.7.0 ; extra == 'lint-template'
Requires-Dist: mypy ==1.5.1 ; extra == 'lint-template'
Requires-Dist: pylint ==2.17.5 ; extra == 'lint-template'
Requires-Dist: pydocstyle[toml] ==6.3.0 ; extra == 'lint-template'
Requires-Dist: pytest ==7.4.1 ; extra == 'lint-template'
Requires-Dist: types-docutils ; extra == 'lint-template'
Requires-Dist: types-setuptools ; extra == 'lint-template'
Requires-Dist: jinja2 ==3.1.2 ; extra == 'lint-template'
Provides-Extra: test
Requires-Dist: pytest ==7.4.1 ; extra == 'test'
Requires-Dist: pytest-randomly ==3.15.0 ; extra == 'test'
Requires-Dist: pytest-cov ==4.1.0 ; extra == 'test'
Requires-Dist: coverage[toml] ==7.3.1 ; extra == 'test'
Provides-Extra: test-template
Requires-Dist: pytest ==7.4.1 ; extra == 'test-template'
Requires-Dist: pytest-randomly ==3.15.0 ; extra == 'test-template'
Requires-Dist: pytest-cov ==4.1.0 ; extra == 'test-template'
Requires-Dist: coverage[toml] ==7.3.1 ; extra == 'test-template'
Provides-Extra: tox
Requires-Dist: tox ==4.11.1 ; extra == 'tox'
